.gitignore
.readthedocs.yml
CHANGELOG.md
LICENSE.txt
MANIFEST.in
README.rst
cliff.toml
poetry.lock
pyproject.toml
setup.py
.github/workflows/auto-tagging.yml
.github/workflows/run-tests.yml
docs/Makefile
docs/conf.py
docs/current_state.png
docs/current_state1.png
docs/edge_type_2-1.png
docs/edge_type_2.png
docs/fig.png
docs/graph.rst
docs/index.rst
docs/installation.rst
docs/make.bat
docs/modules.rst
docs/my_network.png
docs/my_network1.png
docs/network.rst
docs/overview.rst
docs/queues.rst
docs/requirements.txt
docs/sim.png
docs/sim1.png
docs/store.png
docs/store1.png
docs/_static/bootstrap-lumen.min.css
docs/_static/copybutton.js
docs/_static/customized_alabaster.css
docs/_static/jquery.min.js
docs/_static/qt_sphinx13.css
docs/_templates/layout.html
docs/_templates/opensearch.xml
docs/_templates/search.html
docs/_templates/searchbox.html
docs/_templates/searchresults.html
docs/_themes/qt_sphinx13/layout.html
docs/_themes/qt_sphinx13/theme.conf
examples/example_grocery_store.py
queueing_tool/__init__.py
queueing_tool/union_find.py
queueing_tool.egg-info/PKG-INFO
queueing_tool.egg-info/SOURCES.txt
queueing_tool.egg-info/dependency_links.txt
queueing_tool.egg-info/requires.txt
queueing_tool.egg-info/top_level.txt
queueing_tool/graph/__init__.py
queueing_tool/graph/_pairwise.pyx
queueing_tool/graph/graph_functions.py
queueing_tool/graph/graph_generation.py
queueing_tool/graph/graph_preparation.py
queueing_tool/graph/graph_wrapper.py
queueing_tool/network/__init__.py
queueing_tool/network/priority_queue.c
queueing_tool/network/priority_queue.pyx
queueing_tool/network/queue_network.py
queueing_tool/queues/__init__.py
queueing_tool/queues/agents.py
queueing_tool/queues/choice.c
queueing_tool/queues/choice.pyx
queueing_tool/queues/queue_extentions.py
queueing_tool/queues/queue_servers.py
tests/test_graph_generation.py
tests/test_network.py
tests/test_qndigraph.py
tests/test_queue_server.py
tests/test_statistical_properties.py
tests/img/test-mpl-1.x.png
tests/img/test-mpl-2.x.png