Metadata-Version: 2.1
Name: queueing-tool
Version: 1.2.5
Summary: A queueing network simulator
Author-email: Daniel Jordon <dan.jordon@gmail.com>
License: MIT
Project-URL: Documentation, https://queueing-tool.readthedocs.io/en/latest/
Project-URL: Homepage, https://github.com/djordon/queueing-tool
Keywords: queueing theory,queueing,simulation,queueing simulator,queueing network simulation,networks,queueing simulation
Classifier: Development Status :: 4 - Beta
Classifier: Intended Audience :: Science/Research
Classifier: License :: OSI Approved :: MIT License
Classifier: Operating System :: MacOS :: MacOS X
Classifier: Operating System :: Microsoft :: Windows
Classifier: Operating System :: POSIX :: Linux
Classifier: Operating System :: Unix
Classifier: Programming Language :: Python :: 2
Classifier: Programming Language :: Python :: 2.7
Classifier: Programming Language :: Python :: 3
Classifier: Programming Language :: Python :: 3.6
Classifier: Programming Language :: Python :: 3.7
Classifier: Programming Language :: Python :: 3.8
Classifier: Programming Language :: Python :: 3.9
Classifier: Programming Language :: Python :: 3.10
Classifier: Topic :: Scientific/Engineering :: Information Analysis
Classifier: Topic :: Scientific/Engineering :: Mathematics
Requires-Python: !=3.0,!=3.1,!=3.2,>=2.7
Provides-Extra: plotting
License-File: LICENSE.txt
